{
 "BetterGIAddress": "D:\\subject\\lua\\BetterGI",
 "isStartTimeLong": false,
 "isMysSignIn": false,
 "isMoLaSum": false,
 "OneLongHour": 11,
 "OneLongMinute": 4,
 "webhookURL": "https://qyapi.weixin.qq.com",
 "content": "Bgi破溃了",
 "configNames": ["我的","我的","我的","我的","我的","我的","我的"],
 "BagStatistics": "萃凝晶,水晶块,星银矿石,紫晶块,白铁矿,铁块,魔晶块,胡萝卜,鸟蛋,鱼肉,兽肉,禽肉,神秘的肉,鳗肉,螃蟹,薄荷,蘑菇,苹果,竹笋,莲蓬,沉玉仙茗,绝云椒椒,绯樱绣球,帕蒂沙兰,树王圣体菇,清心,海露花,青蜜莓,嘟嘟莲,琉璃袋,钩钩果,小灯草,青蛙,蝴蝶翅膀,晶核,蜥蜴尾巴,电气水晶,烈焰花,冰雾花,烛伞蘑菇,松果,墩墩桃,烬芯花,汐藻,马尾,红果果菇,冷鲜肉,星蕈,澄晶石,石珀,蒲公英种子,肉龙掌",
 "post": ":8083",
 "backups": ["JsScript\\AutoArtifactsPro\\records\\默认账户.txt"],
 "jsName": ["AutoArtifactsPro","AEscoffier_chef"],
 "isControlGroup": true,
 "Cookie": ""
}